viperleed/__init__.py
viperleed/__main__.py
viperleed/calc.mplstyle
viperleed/cli.py
viperleed/cli_base.py
viperleed/calc/__init__.py
viperleed/calc/__main__.py
viperleed/calc/cli.py
viperleed/calc/constants.py
viperleed/calc/from_ase.py
viperleed/calc/psgen.py
viperleed/calc/run.py
viperleed/calc/symmetry.py
viperleed/calc/bookkeeper/__init__.py
viperleed/calc/bookkeeper/__main__.py
viperleed/calc/bookkeeper/bookkeeper.py
viperleed/calc/bookkeeper/cli.py
viperleed/calc/bookkeeper/constants.py
viperleed/calc/bookkeeper/domain_finder.py
viperleed/calc/bookkeeper/errors.py
viperleed/calc/bookkeeper/exit_code.py
viperleed/calc/bookkeeper/log.py
viperleed/calc/bookkeeper/mode.py
viperleed/calc/bookkeeper/root_explorer.py
viperleed/calc/bookkeeper/utils.py
viperleed/calc/bookkeeper/history/__init__.py
viperleed/calc/bookkeeper/history/constants.py
viperleed/calc/bookkeeper/history/errors.py
viperleed/calc/bookkeeper/history/explorer.py
viperleed/calc/bookkeeper/history/folder.py
viperleed/calc/bookkeeper/history/info.py
viperleed/calc/bookkeeper/history/meta.py
viperleed/calc/bookkeeper/history/workhistory.py
viperleed/calc/bookkeeper/history/entry/__init__.py
viperleed/calc/bookkeeper/history/entry/entry.py
viperleed/calc/bookkeeper/history/entry/enums.py
viperleed/calc/bookkeeper/history/entry/field.py
viperleed/calc/bookkeeper/history/entry/field_collection.py
viperleed/calc/bookkeeper/history/entry/list_of_int_field.py
viperleed/calc/bookkeeper/history/entry/notes_field.py
viperleed/calc/bookkeeper/history/entry/rfactor_field.py
viperleed/calc/bookkeeper/history/entry/string_field.py
viperleed/calc/bookkeeper/history/entry/time_field.py
viperleed/calc/classes/__init__.py
viperleed/calc/classes/atom.py
viperleed/calc/classes/atom_containers.py
viperleed/calc/classes/beam.py
viperleed/calc/classes/layer.py
viperleed/calc/classes/r_error.py
viperleed/calc/classes/search_job.py
viperleed/calc/classes/searchpar.py
viperleed/calc/classes/sitetype.py
viperleed-0.14.1.dist-info/licenses/LICENSE.md
viperleed-0.14.1.dist-info/METADATA
viperleed-0.14.1.dist-info/WHEEL
viperleed-0.14.1.dist-info/entry_points.txt
viperleed-0.14.1.dist-info/top_level.txt
viperleed-0.14.1.dist-info/RECORD
