Metadata-Version: 2.4
Name: viperleed
Version: 0.14.1
Summary: Tools for quantitative low-energy electron diffraction
Author: Michele Riva, Florian Kraushofer, Alexander M. Imre, Florian Dörr
Maintainer: ViPErLEED Developers
License: ViPErLEED is a comprehensive set of tools for measuring, processing, and
Project-URL: Homepage, https://viperleed.org
Project-URL: Documentation, https://viperleed.org
Project-URL: Download, https://github.com/viperleed/viperleed/releases
Project-URL: Source, https://github.com/viperleed/viperleed
Project-URL: Issues, https://github.com/viperleed/viperleed/issues
Keywords: LEED,electron,diffraction,IV,I(V),surface,science,physics
Classifier: Intended Audience :: Science/Research
Classifier: Natural Language :: English
Classifier: Operating System :: MacOS
Classifier: Operating System :: Microsoft :: Windows
Classifier: Operating System :: OS Independent
Classifier: Operating System :: POSIX
Classifier: Operating System :: POSIX :: Linux
Classifier: Operating System :: Unix
Classifier: Programming Language :: Python :: 3 :: Only
Classifier: Programming Language :: Python :: 3.7
Classifier: Programming Language :: Python :: 3.8
Classifier: Programming Language :: Python :: 3.9
Classifier: Programming Language :: Python :: 3.10
Classifier: Programming Language :: Python :: 3.11
Classifier: Programming Language :: Python :: 3.12
Classifier: Programming Language :: Python :: 3.13
Classifier: Programming Language :: Python :: 3.14
Classifier: Topic :: Scientific/Engineering :: Physics
Requires-Python: >=3.7
License-File: LICENSE.md
Requires-Dist: fortranformat
Requires-Dist: importlib_resources; python_version < "3.10"
Requires-Dist: matplotlib>=3.5
Requires-Dist: numpy
Requires-Dist: psutil
Requires-Dist: quicktions
Requires-Dist: scipy
Requires-Dist: scikit-learn
Requires-Dist: typing-extensions; python_version < "3.12"
Requires-Dist: wrapt
Provides-Extra: gui
Requires-Dist: PyQt5; extra == "gui"
Requires-Dist: mplcairo; python_version < "3.14" and extra == "gui"
Provides-Extra: hardware
Requires-Dist: requests; extra == "hardware"
Dynamic: license-file
